fakerMM/__init__.py
fakerMM-0.0.4.dist-info/LICENSE.txt
fakerMM-0.0.4.dist-info/METADATA
fakerMM-0.0.4.dist-info/WHEEL
fakerMM-0.0.4.dist-info/top_level.txt
fakerMM-0.0.4.dist-info/RECORD
