Metadata-Version: 2.1
Name: fakerMM
Version: 0.0.4
Summary: datos sinteticos personalizados
Home-page: UNKNOWN
Author: Patricia Perez Villegas
Author-email: 
License: MIT
Keywords: faker
Platform: UNKNOWN
Classifier: Development Status :: 5 - Production/Stable
Classifier: Intended Audience :: Education
Classifier: Operating System :: Microsoft :: Windows :: Windows 10
Classifier: License :: OSI Approved :: MIT License
Classifier: Programming Language :: Python :: 3
License-File: LICENSE.txt
Requires-Dist: faker
